CHANGES.rst
CONTRIBUTORS.rst
MANIFEST.in
README.rst
requirements.txt
setup.cfg
setup.py
docs/LICENSE.GPL
docs/LICENSE.rst
docs/index.rst
src/collective/__init__.py
src/collective.handlebars.egg-info/PKG-INFO
src/collective.handlebars.egg-info/SOURCES.txt
src/collective.handlebars.egg-info/dependency_links.txt
src/collective.handlebars.egg-info/entry_points.txt
src/collective.handlebars.egg-info/namespace_packages.txt
src/collective.handlebars.egg-info/not-zip-safe
src/collective.handlebars.egg-info/requires.txt
src/collective.handlebars.egg-info/top_level.txt
src/collective/handlebars/__init__.py
src/collective/handlebars/configure.zcml
src/collective/handlebars/interfaces.py
src/collective/handlebars/setuphandlers.py
src/collective/handlebars/testing.py
src/collective/handlebars/testing.zcml
src/collective/handlebars/browser/__init__.py
src/collective/handlebars/browser/configure.zcml
src/collective/handlebars/browser/views.py
src/collective/handlebars/browser/static/.gitkeep
src/collective/handlebars/browser/templates/plone_standard_template.pt
src/collective/handlebars/locales/update.sh
src/collective/handlebars/profiles/default/browserlayer.xml
src/collective/handlebars/profiles/default/metadata.xml
src/collective/handlebars/profiles/uninstall/browserlayer.xml
src/collective/handlebars/tests/__init__.py
src/collective/handlebars/tests/test_setup.py
src/collective/handlebars/tests/test_views.py
src/collective/handlebars/tests/data/_slideshow_slide.js.hbs
src/collective/handlebars/tests/data/body_tile.hbs
src/collective/handlebars/tests/data/helper.hbs
src/collective/handlebars/tests/data/helper.html
src/collective/handlebars/tests/data/minimal.hbs
src/collective/handlebars/tests/data/minimal.html
src/collective/handlebars/tests/data/minimal_file.html
src/collective/handlebars/tests/data/minimal_plone.html
src/collective/handlebars/tests/data/minimal_plone_51.html